<toolSet name="External Tools">
  <tool name="css" showInMainMenu="false" showInEditor="false" showInProject="false" showInSearchPopup="false" disabled="false" useConsole="true" showConsoleOnStdOut="true" showConsoleOnStdErr="true" synchronizeAfterRun="true">
    <exec>
      <option name="COMMAND" value="python" />
      <option name="PARAMETERS" value="$USER_HOME$/PycharmProjects/temp/main.py $FilePath$ $SelectionStartLine$ $SelectionStartColumn$ $SelectionEndLine$ $SelectionEndColumn$" />
      <option name="WORKING_DIRECTORY" value="$USER_HOME$/PycharmProjects/temp" />
    </exec>
  </tool>
  <tool name="__css" showInMainMenu="false" showInEditor="false" showInProject="false" showInSearchPopup="false" disabled="false" useConsole="true" showConsoleOnStdOut="true" showConsoleOnStdErr="true" synchronizeAfterRun="true">
    <exec>
      <option name="COMMAND" value="C:\Users\ellen\CLionProjects\untitled5\cmake-build-debug\untitled5.exe" />
      <option name="PARAMETERS" value="$FilePath$ $SelectionStartLine$ $SelectionStartColumn$ $SelectionEndLine$ $SelectionEndColumn$" />
      <option name="WORKING_DIRECTORY" value="$USER_HOME$/PycharmProjects/temp" />
    </exec>
  </tool>
</toolSet>